thumpy/Lenna.png
thumpy/__init__.py
thumpy/thumpy_tests.py
thumpy-0.3.2.dist-info/DESCRIPTION.rst
thumpy-0.3.2.dist-info/METADATA
thumpy-0.3.2.dist-info/RECORD
thumpy-0.3.2.dist-info/WHEEL
thumpy-0.3.2.dist-info/entry_points.txt
thumpy-0.3.2.dist-info/metadata.json
thumpy-0.3.2.dist-info/top_level.txt
