Metadata-Version: 2.0
Name: thumpy
Version: 0.3.2
Summary: A Python web server that uses Pillow to dynamically scale, crop, transform and serve images from S3 or the local filesystem
Home-page: https://github.com/btubbs/thumpy
Author: Brent Tubbs/Berry Phillips
Author-email: brent.tubbs@gmail.com/berryphillips@gmail.com
License: UNKNOWN
Platform: UNKNOWN
Requires-Dist: boto (==2.1.0)
Requires-Dist: gevent (==0.13.6)
Requires-Dist: pillow (==3.2.0)
Requires-Dist: pyyaml (==3.10)
